cloudbackup/__init__.py
cloudbackup/client/__init__.py
cloudbackup/client/agents.py
cloudbackup/client/auth.py
cloudbackup/client/backup.py
cloudbackup/client/deuce.py
cloudbackup/client/rse.py
cloudbackup/cloud/__init__.py
cloudbackup/cloud/files.py
cloudbackup/cmd/__init__.py
cloudbackup/cmd/shell/__init__.py
cloudbackup/cmd/shell/exceptions.py
cloudbackup/cmd/shell/interface.py
cloudbackup/cmd/shell/prompter.py
cloudbackup/common/__init__.py
cloudbackup/common/command.py
cloudbackup/database/__init__.py
cloudbackup/database/sqlite.py
cloudbackup/tests/__init__.py
cloudbackup/tests/integration/__init__.py
cloudbackup/tests/smoke/__init__.py
cloudbackup/tests/unit/__init__.py
cloudbackup/utils/__init__.py
cloudbackup/utils/dc.py
cloudbackup/utils/menus.py
cloudbackup/utils/printer.py
cloudbackup/utils/tz.py
python_cloudbackup_sdk-0.20.0.dist-info/DESCRIPTION.rst
python_cloudbackup_sdk-0.20.0.dist-info/METADATA
python_cloudbackup_sdk-0.20.0.dist-info/RECORD
python_cloudbackup_sdk-0.20.0.dist-info/WHEEL
python_cloudbackup_sdk-0.20.0.dist-info/entry_points.txt
python_cloudbackup_sdk-0.20.0.dist-info/metadata.json
python_cloudbackup_sdk-0.20.0.dist-info/top_level.txt
