Metadata-Version: 2.0
Name: python-cloudbackup-sdk
Version: 0.20.0
Summary: A Python client for the Rackspace Cloud Backup API.
Home-page: https://github.com/rackerlabs/python-cloudbackup-sdk
Author: Alejandro Cabrera, Benjamen Meyer
Author-email: CloudBackup@rackspace.com
License: Apache License (2.0)
Keywords: rackspace,Cloud Backup,client
Platform: UNKNOWN
Classifier: Development Status :: 4 - Beta
Classifier: License :: OSI Approved :: Apache Software License
Classifier: Environment :: Console
Classifier: Operating System :: OS Independent
Classifier: Intended Audience :: Developers
Classifier: Intended Audience :: System Administrators
Classifier: Programming Language :: Python :: 2.7
Classifier: Programming Language :: Python :: 3.3
Classifier: Programming Language :: Python :: 3.4
Classifier: Programming Language :: Python :: Implementation :: CPython
Requires-Dist: pytz (==2013.9)
Requires-Dist: requests (>=2.3.0)
Requires-Dist: tzlocal (==1.1.1)
